sunkhronos/__init__.py
sunkhronos/client/Factory.py
sunkhronos/client/Protocol.py
sunkhronos/client/__init__.py
sunkhronos/fs/FSManager.py
sunkhronos/fs/__init__.py
sunkhronos/server/Factory.py
sunkhronos/server/Protocol.py
sunkhronos/server/__init__.py
sunkhronos/sync/Synchroniser.py
sunkhronos/sync/__init__.py
sunkhronos/sync/diff3lib.py
sunkhronos/sync/merge.py
sunkhronos-0.0.1.dist-info/DESCRIPTION.rst
sunkhronos-0.0.1.dist-info/METADATA
sunkhronos-0.0.1.dist-info/RECORD
sunkhronos-0.0.1.dist-info/WHEEL
sunkhronos-0.0.1.dist-info/entry_points.txt
sunkhronos-0.0.1.dist-info/metadata.json
sunkhronos-0.0.1.dist-info/top_level.txt
