Metadata-Version: 2.0
Name: sunkhronos
Version: 0.0.1
Summary: Keep two folders on different devices in sync
Home-page: https://github.com/pbaisla/sunkhronos
Author: Prashant Baisla
Author-email: prashantbaisla@gmail.com
License: License :: OSI Approved :: GNU General Public License v2 (GPLv2)
Keywords: folder directory sync
Platform: UNKNOWN
Classifier: Development Status :: 3 - Alpha
Requires-Python: >=3
Requires-Dist: twisted
Requires-Dist: watchdog
Provides-Extra: dev
Requires-Dist: check-manifest; extra == 'dev'
Provides-Extra: test
Requires-Dist: coverage; extra == 'test'
